nonebot_poe_chat/__init__.py
nonebot_poe_chat/config.py
nonebot_poe_chat/poe_api.py
nonebot_poe_chat/poe_func.py
nonebot_poe_chat/pwframework.py
nonebot_poe_chat/txt2img.py
nonebot_poe_chat/TXT2IMG/font/sarasa-mono-sc-regular.ttf
nonebot_poe_chat/TXT2IMG/image/background.png
nonebot_poe_chat/TXT2IMG/image/banner.png
nonebot_poe_chat/TXT2IMG/image/mi_background.png
nonebot_poe_chat-1.1.9.dist-info/LICENSE.txt
nonebot_poe_chat-1.1.9.dist-info/METADATA
nonebot_poe_chat-1.1.9.dist-info/WHEEL
nonebot_poe_chat-1.1.9.dist-info/top_level.txt
nonebot_poe_chat-1.1.9.dist-info/RECORD
