Metadata-Version: 2.1
Name: nonebot-poe-chat
Version: 1.1.9
Summary: nonebot_poe_chat
Home-page: https://github.com/canxin121/nonebot_poe_chat
Author: canxin
Author-email: 1969730106@qq.com
Classifier: Programming Language :: Python :: 3.10
Classifier: Programming Language :: Python :: 3.9
Classifier: Programming Language :: Python :: 3.8
Classifier: License :: OSI Approved :: GNU Affero General Public License v3
Classifier: Operating System :: OS Independent
License-File: LICENSE.txt
Requires-Dist: nonebot2 (>=2.0.0rc3)
Requires-Dist: nonebot-adapter-onebot (>=2.0.0b1)
Requires-Dist: nonebot-plugin-guild-patch (>=0.2.3)
Requires-Dist: playwright (>=1.32.1)
Requires-Dist: aiohttp (>=3.8.4)
Requires-Dist: Pillow (>=9.5.0)
Requires-Dist: qrcode (>=7.4.2)
